reportxlsxforlinux/__init__.py
reportxlsxforlinux/to_excel.py
reportxlsxforlinux/resources/linux/SkiaSharp.dll
reportxlsxforlinux/resources/linux/Spire.XLS.dll
reportxlsxforlinux/resources/windows/Spire.XLS.dll
reportxlsxforlinux-0.0.5.dist-info/METADATA
reportxlsxforlinux-0.0.5.dist-info/WHEEL
reportxlsxforlinux-0.0.5.dist-info/top_level.txt
reportxlsxforlinux-0.0.5.dist-info/RECORD
