Metadata-Version: 2.1
Name: reportxlsxforlinux
Version: 0.0.5
Summary: 这是一个操作xlsx的库,只为linux而生
Home-page: https://github.com/bailulue
Author: bailu
Author-email: yabailu@chinatelecom.cn
License: UNKNOWN
Platform: UNKNOWN
Requires-Dist: pandas
Requires-Dist: openpyxl
Requires-Dist: pythonnet
Requires-Dist: aspose-cells (==24.5.0)
